<?xml version="1.0" encoding="utf-8" ?>

<collections>
	<collection>
		<name>0</name>
		<entry>Detect poison</entry>
		<entry>Read magic</entry>
		<entry>Create water</entry>
		<entry>Cure minor wounds</entry>
		<entry>Detect magic</entry>
		<entry>Guidance</entry>
		<entry>Light</entry>
		<entry>Mending</entry>
		<entry>Purify food and drink</entry>
		<entry>Resistance</entry>
		<entry>Virtue</entry>
		<entry>Flare</entry>
		<entry>Know direction</entry>
	</collection>
	<collection>
		<name>1</name>
		<entry>Cure light wounds</entry>
		<entry>Endure elements</entry>
		<entry>Magic stone</entry>
		<entry>Obscuring mist</entry>
		<entry>Summon nature's ally I</entry>
		<entry>Charm animal</entry>
		<entry>Calm animals</entry>
		<entry>Detect animals or plants</entry>
		<entry>Detect snares and pits</entry>
		<entry>Entangle</entry>
		<entry>Faerie fire</entry>
		<entry>Goodberry</entry>
		<entry>Hide from animals</entry>
		<entry>Jump</entry>
		<entry>Longstrider</entry>
		<entry>Magic fang</entry>
		<entry>Pass without trace</entry>
		<entry>Produce flame</entry>
		<entry>Speak with animals</entry>
		<entry>Shillelagh</entry>
	</collection>
	<collection>
		<name>2</name>
		<entry>Delay poison</entry>
		<entry>Resist energy</entry>
		<entry>Bear's endurance</entry>
		<entry>Owl's wisdom</entry>
		<entry>Bull's strength</entry>
		<entry>Lesser restoration</entry>
		<entry>Summon nature's ally II</entry>
		<entry>Animal trance</entry>
		<entry>Barkskin</entry>
		<entry>Cat's grace</entry>
		<entry>Chill metal</entry>
		<entry>Fire trap</entry>
		<entry>Flame blade</entry>
		<entry>Flaming sphere</entry>
		<entry>Fog cloud</entry>
		<entry>Gust of wind</entry>
		<entry>Heat metal</entry>
		<entry>Hold animal</entry>
		<entry>Reduce animal</entry>
		<entry>Soften earth and stone</entry>
		<entry>Spider climb</entry>
		<entry>Summon swarm</entry>
		<entry>Tree shape</entry>
		<entry>Warp wood</entry>
		<entry>Wood shape</entry>
		<entry>Animal messenger</entry>
	</collection>
	<collection>
		<name>3</name>
		<entry>Cure moderate wounds</entry>
		<entry>Neutralize poison</entry>
		<entry>Remove disease</entry>
		<entry>Protection from energy</entry>
		<entry>Wind wall</entry>
		<entry>Contagion</entry>
		<entry>Daylight</entry>
		<entry>Meld into stone</entry>
		<entry>Poison</entry>
		<entry>Stone shape</entry>
		<entry>Summon nature's ally III</entry>
		<entry>Water breathing</entry>
		<entry>Call lightning</entry>
		<entry>Diminish plants</entry>
		<entry>Dominate animal</entry>
		<entry>Greater magic fang</entry>
		<entry>Plant growth</entry>
		<entry>Quench</entry>
		<entry>Sleet storm</entry>
		<entry>Snare</entry>
		<entry>Speak with plants</entry>
		<entry>Spike growth</entry>
	</collection>
	<collection>
		<name>4</name>
		<entry>Cure serious wounds</entry>
		<entry>Freedom of movement</entry>
		<entry>Repel vermin</entry>
		<entry>Air walk</entry>
		<entry>Control water</entry>
		<entry>Dispel magic</entry>
		<entry>Flame strike</entry>
		<entry>Giant vermin</entry>
		<entry>Scrying</entry>
		<entry>Summon nature's ally IV</entry>
		<entry>Antiplant shell</entry>
		<entry>Blight</entry>
		<entry>Command plants</entry>
		<entry>Ice storm</entry>
		<entry>Reincarnate</entry>
		<entry>Rusting grasp</entry>
		<entry>Spike stones</entry>
	</collection>
	<collection>
		<name>5</name>
		<entry>Atonement</entry>
		<entry>Cure critical wounds</entry>
		<entry>Death ward</entry>
		<entry>Hallow</entry>
		<entry>Insect plague</entry>
		<entry>Summon nature's ally V</entry>
		<entry>Unhallow</entry>
		<entry>Animal growth</entry>
		<entry>Awaken</entry>
		<entry>Baleful polymorph</entry>
		<entry>Call lightning storm</entry>
		<entry>Commune with nature</entry>
		<entry>Control winds</entry>
		<entry>Stoneskin</entry>
		<entry>Transmute mud to rock</entry>
		<entry>Transmute rock to mud</entry>
		<entry>Tree stride</entry>
		<entry>Wall of fire</entry>
		<entry>Wall of thorns</entry>
	</collection>
	<collection>
		<name>6</name>
		<entry>Antilife shell</entry>
		<entry>Find the path</entry>
		<entry>Greater dispel magic</entry>
		<entry>Mass bear's endurance</entry>
		<entry>Mass bull's strength</entry>
		<entry>Mass owl's wisdom</entry>
		<entry>Mass cure light wounds</entry>
		<entry>Summon nature's ally VI</entry>
		<entry>Wall of stone</entry>
		<entry>Fire seeds</entry>
		<entry>Ironwood</entry>
		<entry>Liveoak</entry>
		<entry>Mass cat's grace</entry>
		<entry>Move earth</entry>
		<entry>Repel wood</entry>
		<entry>Spellstaff</entry>
		<entry>Stone tell</entry>
		<entry>Transport via plants</entry>
	</collection>
	<collection>
		<name>7</name>
		<entry>Control weather</entry>
		<entry>Fire storm</entry>
		<entry>Greater scrying</entry>
		<entry>Heal</entry>
		<entry>Mass cure moderate wounds</entry>
		<entry>Summon nature's ally VII</entry>
		<entry>True seeing</entry>
		<entry>Wind walk</entry>
		<entry>Animate plants</entry>
		<entry>Changestaff</entry>
		<entry>Creeping doom</entry>
		<entry>Sunbeam</entry>
		<entry>Transmute metal to wood</entry>
	</collection>
	<collection>
		<name>8</name>
		<entry>Earthquake</entry>
		<entry>Mass cure serious wounds</entry>
		<entry>Summon nature's ally VIII</entry>
		<entry>Word of recall</entry>
		<entry>Animal shapes</entry>
		<entry>Control plants</entry>
		<entry>Finger of death</entry>
		<entry>Repel metal or stone</entry>
		<entry>Reverse gravity</entry>
		<entry>Sunburst</entry>
		<entry>Whirlwind</entry>
	</collection>
	<collection>
		<name>9</name>
		<entry>Mass cure critical wounds</entry>
		<entry>Regenerate</entry>
		<entry>Storm of vengeance</entry>
		<entry>Summon nature's ally IX</entry>
		<entry>Antipathy</entry>
		<entry>Elemental swarm</entry>
		<entry>Foresight</entry>
		<entry>Shambler</entry>
		<entry>Shapechange</entry>
		<entry>Sympathy</entry>
	</collection>
</collections>