<?xml version="1.0" encoding="utf-8" ?>

<items>
    <object>
        <name>Natural Armor</name>
        <item>Natural Armor</item>
        <item></item>
        <item>0</item>
        <item>2</item>
        <item></item>
        <item>0</item>
        <item></item>
      <item>0</item>
      <item></item>
      <item>0</item>
    </object>
  <object>
    <name>Empathy</name>
    <item>Empathy</item>
    <item></item>
    <item>0</item>
    <item>4</item>
    <item>Boar</item>
    <item>0</item>
    <item></item>
    <item>0</item>
    <item></item>
    <item>0</item>
  </object>
  <object>
    <name>Lycanthropy</name>
    <item>Lycanthropy</item>
    <item></item>
    <item>0</item>
    <item>0</item>
    <item>Wereboar</item>
    <item>0</item>
    <item></item>
    <item>0</item>
    <item></item>
    <item>0</item>
  </object>
  <object>
    <name>Alternate Form</name>
    <item>Alternate Form</item>
    <item></item>
    <item>0</item>
    <item>0</item>
    <item>Boar</item>
    <item>0</item>
    <item></item>
    <item>0</item>
    <item></item>
    <item>0</item>
  </object>
  <object>
    <name>Scent</name>
    <item>Scent</item>
    <item></item>
    <item>0</item>
    <item>0</item>
    <item></item>
    <item>0</item>
    <item></item>
    <item>0</item>
    <item></item>
    <item>0</item>
  </object>
  <object>
    <name>Ferocity</name>
    <item>Ferocity</item>
    <item></item>
    <item>0</item>
    <item>0</item>
    <item></item>
    <item>0</item>
    <item></item>
    <item>0</item>
    <item></item>
    <item>0</item>
  </object>
    <object>
        <name>Low-Light Vision</name>
        <item>Low-Light Vision</item>
        <item></item>
        <item>0</item>
        <item>0</item>
        <item></item>
        <item>0</item>
        <item></item>
      <item>0</item>
      <item></item>
      <item>0</item>
    </object>
    <object>
      <name>Save BonusFortitude</name>
      <item>Save Bonus</item>
      <item></item>
      <item>0</item>
      <item>3</item>
      <item>Fortitude</item>
      <item>0</item>
      <item></item>
      <item>0</item>
      <item></item>
      <item>0</item>
  </object>
  <object>
    <name>Save BonusReflex</name>
    <item>Save Bonus</item>
    <item></item>
    <item>0</item>
    <item>3</item>
    <item>Reflex</item>
    <item>0</item>
    <item></item>
    <item>0</item>
    <item></item>
    <item>0</item>
  </object>
  <object>
    <name>Save BonusWill</name>
    <item>Save Bonus</item>
    <item></item>
    <item>0</item>
    <item>1</item>
    <item>Will</item>
    <item>0</item>
    <item></item>
    <item>0</item>
    <item></item>
    <item>0</item>
  </object>
  <object>
    <name>Skill BonusListen</name>
    <item>Skill Bonus</item>
    <item></item>
    <item>0</item>
    <item>3</item>
    <item>Listen</item>
    <item>0</item>
    <item></item>
    <item>0</item>
    <item></item>
    <item>0</item>
  </object>
  <object>
    <name>Skill BonusSpot</name>
    <item>Skill Bonus</item>
    <item></item>
    <item>0</item>
    <item>3</item>
    <item>Spot</item>
    <item>0</item>
    <item></item>
    <item>0</item>
    <item></item>
    <item>0</item>
  </object>
</items>